{
  "main": {
    "id": "bb4bd613ce94b7eb",
    "type": "split",
    "children": [
      {
        "id": "a1a3e1f4e0b4ad08",
        "type": "tabs",
        "children": [
          {
            "id": "acff9bc59b3fb50e",
            "type": "leaf",
            "state": {
              "type": "markdown",
              "state": {
                "file": "Anotações Estudos/(PROG) Front-End/JavaScript/JavaScript - Orientação/JavaScript - Cápitulo 9.md",
                "mode": "source",
                "source": false
              }
            }
          },
          {
            "id": "b66a9a1c6ab0c3b3",
            "type": "leaf",
            "state": {
              "type": "graph",
              "state": {}
            }
          },
          {
            "id": "9092ff1207a0162c",
            "type": "leaf",
            "state": {
              "type": "markdown",
              "state": {
                "file": "Anotações Estudos/(PROG) Front-End/JavaScript/JavaScript - Conteúdo/Teoria/09 - Programação Assincrona/9.3 - Promises/9.3.3 - Resolvendo várias Promises.md",
                "mode": "source",
                "source": false
              }
            }
          },
          {
            "id": "61dff206fe1fa9a2",
            "type": "leaf",
            "state": {
              "type": "markdown",
              "state": {
                "file": "Anotações Estudos/(PROG) Front-End/JavaScript/JavaScript - Conteúdo/Teoria/09 - Programação Assincrona/9.3 - Promises/9.3.2 - Rejeitando Promises.md",
                "mode": "source",
                "source": false
              }
            }
          },
          {
            "id": "5609df9945b749d1",
            "type": "leaf",
            "state": {
              "type": "markdown",
              "state": {
                "file": "Anotações Estudos/(PROG) Front-End/JavaScript/JavaScript - Conteúdo/Teoria/09 - Programação Assincrona/9.3 - Promises/9.3.1 - Falha nas Promises.md",
                "mode": "source",
                "source": false
              }
            }
          }
        ],
        "currentTab": 1
      }
    ],
    "direction": "vertical"
  },
  "left": {
    "id": "6176fb5b715d1e1c",
    "type": "split",
    "children": [
      {
        "id": "1dd7dd8d17bc190c",
        "type": "tabs",
        "children": [
          {
            "id": "04ff579ec1d4fa0a",
            "type": "leaf",
            "state": {
              "type": "file-explorer",
              "state": {
                "sortOrder": "alphabetical"
              }
            }
          },
          {
            "id": "53524a2042b9ed90",
            "type": "leaf",
            "state": {
              "type": "search",
              "state": {
                "query": "",
                "matchingCase": false,
                "explainSearch": false,
                "collapseAll": false,
                "extraContext": false,
                "sortOrder": "alphabetical"
              }
            }
          },
          {
            "id": "551b7fa62e6f8de4",
            "type": "leaf",
            "state": {
              "type": "starred",
              "state": {}
            }
          }
        ]
      }
    ],
    "direction": "horizontal",
    "width": 435.5
  },
  "right": {
    "id": "cf38b8c0fdaa558f",
    "type": "split",
    "children": [
      {
        "id": "07cf707cc21cbd83",
        "type": "tabs",
        "children": [
          {
            "id": "4abd364081f1c334",
            "type": "leaf",
            "state": {
              "type": "backlink",
              "state": {
                "collapseAll": false,
                "extraContext": false,
                "sortOrder": "alphabetical",
                "showSearch": false,
                "searchQuery": "",
                "backlinkCollapsed": false,
                "unlinkedCollapsed": true
              }
            }
          },
          {
            "id": "802057e2d78cb60f",
            "type": "leaf",
            "state": {
              "type": "outgoing-link",
              "state": {
                "linksCollapsed": false,
                "unlinkedCollapsed": true
              }
            }
          },
          {
            "id": "0c9c42d5a559d617",
            "type": "leaf",
            "state": {
              "type": "tag",
              "state": {
                "sortOrder": "frequency",
                "useHierarchy": true
              }
            }
          },
          {
            "id": "d243802c6092ec48",
            "type": "leaf",
            "state": {
              "type": "outline",
              "state": {}
            }
          }
        ]
      }
    ],
    "direction": "horizontal",
    "width": 300,
    "collapsed": true
  },
  "active": "b66a9a1c6ab0c3b3",
  "lastOpenFiles": [
    "Anotações Estudos/(PROG) Front-End/JavaScript/JavaScript - Conteúdo/Teoria/10 - JavaScript no Navegador/10.8 - Criando Nós/10.8.1 - Criando Nós de Texto.md",
    "Anotações Estudos/(PROG) Front-End/JavaScript/JavaScript - Conteúdo/Teoria/10 - JavaScript no Navegador/10.7 - Alterando a DOM/10.7.1 - Alterando a DOM com appendChild.md",
    "Anotações Estudos/(PROG) Front-End/JavaScript/JavaScript - Conteúdo/Teoria/10 - JavaScript no Navegador/10.5 - Encontrando Elementos/10.5.1 - Encontrando Elementos - Por Tag.md",
    "Anotações Estudos/(PROG) Front-End/JavaScript/JavaScript - Conteúdo/Teoria/10 - JavaScript no Navegador/10.4 - O DOM/10.4.1 - A árvore do DOM.md",
    "Anotações Estudos/(PROG) Front-End/JavaScript/JavaScript - Conteúdo/Teoria/10 - JavaScript no Navegador/10.1 - A Web/10.1 - A Web - HTML/10.1.1.1 - A Web - HTML Parte 2.md",
    "Anotações Estudos/(PROG) Front-End/JavaScript/JavaScript - Conteúdo/Teoria/10 - JavaScript no Navegador/10.1 - A Web/10.1.1 - A Web - Protocolos.md",
    "Anotações Estudos/(PROG) Front-End/JavaScript/JavaScript - Conteúdo/Teoria/10 - JavaScript no Navegador/10.1 - A Web.md",
    "Anotações Estudos/(PROG) Front-End/JavaScript/JavaScript - Orientação/Indice JavaScript - Teoria.md",
    "Anotações Estudos/(PROG) Front-End/JavaScript/JavaScript - Conteúdo/Teoria/09 - Programação Assincrona/9.1 - O que é Programação Assíncrona.md",
    "Anotações Estudos/(PROG) Front-End/JavaScript/JavaScript - Conteúdo/Teoria/09 - Programação Assincrona/9.3 - Promises/9.3.1 - Falha nas Promises.md"
  ]
}